{
  "version": 5,
  "cmakeMinimumRequired": {
    "major": 3,
    "minor": 22,
    "patch": 0
  },
  "configurePresets": [
    {
      "name": "windows-msvc-debug",
      "displayName": "Windows MSVC Debug",
      "generator": "Visual Studio 17 2022",
      "binaryDir": "${sourceDir}/build/windows-msvc-debug",
      "cacheVariables": {
        "CMAKE_BUILD_TYPE": "Debug",
        "CMAKE_CONFIGURATION_TYPES": "Debug",
        "DUSTBOX_ENABLE_WARNINGS": "ON",
        "DUSTBOX_STRICT_BUILD": "OFF"
      }
    },
    {
      "name": "windows-msvc-release",
      "displayName": "Windows MSVC Release",
      "generator": "Visual Studio 17 2022",
      "binaryDir": "${sourceDir}/build/windows-msvc-release",
      "cacheVariables": {
        "CMAKE_BUILD_TYPE": "Release",
        "CMAKE_CONFIGURATION_TYPES": "Release",
        "DUSTBOX_ENABLE_WARNINGS": "ON",
        "DUSTBOX_STRICT_BUILD": "OFF"
      }
    },
    {
      "name": "ninja-release",
      "displayName": "Ninja Release (MSVC)",
      "generator": "Ninja",
      "binaryDir": "${sourceDir}/build/ninja-release",
      "cacheVariables": {
        "CMAKE_BUILD_TYPE": "Release",
        "CMAKE_C_COMPILER": "cl.exe",
        "CMAKE_CXX_COMPILER": "cl.exe",
        "DUSTBOX_ENABLE_WARNINGS": "ON",
        "DUSTBOX_STRICT_BUILD": "OFF"
      }
    },
    {
      "name": "macos-xcode-debug",
      "displayName": "macOS Xcode Debug",
      "generator": "Xcode",
      "binaryDir": "${sourceDir}/build/macos-xcode-debug",
      "cacheVariables": {
        "CMAKE_CONFIGURATION_TYPES": "Debug",
        "DUSTBOX_ENABLE_WARNINGS": "ON",
        "DUSTBOX_STRICT_BUILD": "OFF"
      }
    },
    {
      "name": "macos-xcode-release",
      "displayName": "macOS Xcode Release",
      "generator": "Xcode",
      "binaryDir": "${sourceDir}/build/macos-xcode-release",
      "cacheVariables": {
        "CMAKE_CONFIGURATION_TYPES": "Release",
        "DUSTBOX_ENABLE_WARNINGS": "ON",
        "DUSTBOX_STRICT_BUILD": "OFF"
      }
    },
    {
      "name": "ci-strict",
      "displayName": "CI Strict Build",
      "inherits": ["windows-msvc-release"],
      "cacheVariables": {
        "DUSTBOX_STRICT_BUILD": "ON"
      }
    }
  ],
  "buildPresets": [
    {
      "name": "windows-msvc-debug",
      "configurePreset": "windows-msvc-debug"
    },
    {
      "name": "windows-msvc-release",
      "configurePreset": "windows-msvc-release"
    },
    {
      "name": "ninja-release",
      "configurePreset": "ninja-release"
    },
    {
      "name": "macos-xcode-debug",
      "configurePreset": "macos-xcode-debug"
    },
    {
      "name": "macos-xcode-release",
      "configurePreset": "macos-xcode-release"
    },
    {
      "name": "ci-strict",
      "configurePreset": "ci-strict"
    }
  ]
}
